metofficedatahub/__init__.py
metofficedatahub/app.py
metofficedatahub/base.py
metofficedatahub/constants.py
metofficedatahub/models.py
metofficedatahub/multiple_files.py
metofficedatahub/utils.py
metoffice_weather_datahub-1.2.3.dist-info/LICENSE
metoffice_weather_datahub-1.2.3.dist-info/METADATA
metoffice_weather_datahub-1.2.3.dist-info/WHEEL
metoffice_weather_datahub-1.2.3.dist-info/top_level.txt
metoffice_weather_datahub-1.2.3.dist-info/RECORD
