Metadata-Version: 2.1
Name: metoffice-weather-datahub
Version: 1.2.3
Summary: Python wrapper for the UK Met Office Weather DataHub API
Author: Peter Dudfield
Author-email: info@openclimatefix.org
License: MIT
License-File: LICENSE
Requires-Dist: pydantic
Requires-Dist: requests
Requires-Dist: pre-commit
Requires-Dist: ecmwflibs
Requires-Dist: eccodes
Requires-Dist: cfgrib
Requires-Dist: ocf-blosc2
Requires-Dist: xarray
Requires-Dist: numcodecs (==0.10.0a2)
Requires-Dist: zarr
Requires-Dist: fsspec
Requires-Dist: s3fs
Requires-Dist: h5netcdf
Requires-Dist: scipy
Requires-Dist: dask
Requires-Dist: nowcasting-datamodel (==0.0.38)
Requires-Dist: pathy
Requires-Dist: pyproj
Requires-Dist: psutil
